toolforge/__init__.py
wmflabs/__init__.py
wmflabs-3.3.0.dist-info/DESCRIPTION.rst
wmflabs-3.3.0.dist-info/METADATA
wmflabs-3.3.0.dist-info/RECORD
wmflabs-3.3.0.dist-info/WHEEL
wmflabs-3.3.0.dist-info/metadata.json
wmflabs-3.3.0.dist-info/top_level.txt
